nanome_docking/ComplexUtils.py
nanome_docking/Docking.py
nanome_docking/_DockingCalculations.py
nanome_docking/_DockingCalculationsAutodock4.py
nanome_docking/_DockingCalculationsRhodium.py
nanome_docking/_DockingMenu.py
nanome_docking/_DockingMenuRhodium.py
nanome_docking/__init__.py
nanome_docking/_advanced_settings.json
nanome_docking/_docking_menu.json
nanome_docking/_docking_menu_rhodium.json
nanome_docking/checkmark.png
nanome_docking/none.png
nanome_docking/prepare_dpf42.py
nanome_docking/prepare_gpf4.py
nanome_docking/prepare_ligand4.py
nanome_docking/prepare_receptor4.py
nanome_docking/smina
nanome_docking/swri_logo.png
nanome_docking-0.2.1.dist-info/LICENSE
nanome_docking-0.2.1.dist-info/METADATA
nanome_docking-0.2.1.dist-info/WHEEL
nanome_docking-0.2.1.dist-info/entry_points.txt
nanome_docking-0.2.1.dist-info/top_level.txt
nanome_docking-0.2.1.dist-info/RECORD
